{"objects":[{"jobObject":{"JobType":".OrchestrationJob","id":4509,"revision":98,"created":1638283539871,"timestamp":1638283539871,"components":{"4512":{"id":4512,"inputCardinality":"ZERO","outputCardinality":"MANY","connectorHint":"UNCONDITIONAL","executionHint":"FLOW","implementationID":444132438,"x":-224,"y":0,"width":32,"height":32,"inputConnectorIDs":[],"outputSuccessConnectorIDs":[],"outputFailureConnectorIDs":[],"outputUnconditionalConnectorIDs":[4516],"outputTrueConnectorIDs":[],"outputFalseConnectorIDs":[],"exportMappings":{},"parameters":{"1":{"slot":1,"name":"Name","elements":{"1":{"slot":1,"values":{"1":{"slot":1,"type":"STRING","value":"Start 0"}}}},"visible":true}},"activationStatus":"ENABLED","outputIterationConnectorIDs":[],"inputIterationConnectorIDs":[]},"4514":{"id":4514,"inputCardinality":"ONE","outputCardinality":"MANY","connectorHint":"SUCCESS_FAIL","executionHint":"EXECUTE","implementationID":-30576616,"x":-96,"y":0,"width":32,"height":32,"inputConnectorIDs":[4516],"outputSuccessConnectorIDs":[4641,4551],"outputFailureConnectorIDs":[],"outputUnconditionalConnectorIDs":[],"outputTrueConnectorIDs":[],"outputFalseConnectorIDs":[],"exportMappings":{},"parameters":{"1":{"slot":1,"name":"Name","elements":{"1":{"slot":1,"values":{"1":{"slot":1,"type":"STRING","value":"Check variables"}}}},"visible":true},"2":{"slot":2,"name":"Script","elements":{"1":{"slot":1,"values":{"1":{"slot":1,"type":"STRING","value":"# Check that the variables examples_storage and examples_schema exist\n# and have valid default values\n\nif [ -z \"${examples_storage}\" ]\nthen\n\techo \"You must set a default value for examples_storage under Project / Manage Environment Variables\"\n    exit 99\nelse\n\techo \"examples_storage = '${examples_storage}'\"\nfi\n\nif [[ ${examples_storage} == s3* ]]\nthen\n\techo \"The default value for examples_storage must not start with s3://\"\n    exit 99\nfi\n\nif [ -z \"${examples_schema}\" ]\nthen\n\techo \"You must set a default value for examples_schema under Project / Manage Environment Variables\"\n    exit 99\nelse\n\techo \"examples_schema = '${examples_schema}'\"\nfi\n"}}}},"visible":true},"3":{"slot":3,"name":"Timeout","elements":{"1":{"slot":1,"values":{"1":{"slot":1,"type":"INTEGER","value":"360"}}}},"visible":true}},"activationStatus":"ENABLED","outputIterationConnectorIDs":[],"inputIterationConnectorIDs":[]},"4550":{"id":4550,"inputCardinality":"ONE","outputCardinality":"MANY","connectorHint":"SUCCESS_FAIL","executionHint":"EXECUTE","implementationID":620619864,"x":80,"y":-64,"width":32,"height":32,"inputConnectorIDs":[4551],"outputSuccessConnectorIDs":[4689],"outputFailureConnectorIDs":[],"outputUnconditionalConnectorIDs":[],"outputTrueConnectorIDs":[],"outputFalseConnectorIDs":[],"exportMappings":{},"parameters":{"1":{"slot":1,"name":"Name","elements":{"1":{"slot":1,"values":{"1":{"slot":1,"type":"STRING","value":"Plate Boundaries"}}}},"visible":true},"2":{"slot":2,"name":"Source Type","elements":{"1":{"slot":1,"values":{"1":{"slot":1,"type":"STRING","value":"HTTPS"}}}},"visible":true},"4":{"slot":4,"name":"Target Object Name","elements":{"1":{"slot":1,"values":{"1":{"slot":1,"type":"STRING","value":"matillion-examples/spatial/PB2002-LineString.csv.gz"}}}},"visible":true},"5":{"slot":5,"name":"Target Type","elements":{"1":{"slot":1,"values":{"1":{"slot":1,"type":"STRING","value":"S3"}}}},"visible":true},"6":{"slot":6,"name":"Set Home Directory as Root","elements":{"1":{"slot":1,"values":{"1":{"slot":1,"type":"STRING","value":"No"}}}},"visible":false},"7":{"slot":7,"name":"Source URL","elements":{"1":{"slot":1,"values":{"1":{"slot":1,"type":"STRING","value":"ftp://[username[:password]@]hostname[:port][path]"}}}},"visible":false},"8":{"slot":8,"name":"Source Username","elements":{"1":{"slot":1,"values":{"1":{"slot":1,"type":"STRING","value":""}}}},"visible":false},"9":{"slot":9,"name":"Source Password","elements":{"1":{"slot":1,"values":{"1":{"slot":1,"type":"PASSWORD","value":""}}}},"visible":false},"10":{"slot":10,"name":"Source URL","elements":{},"visible":false},"11":{"slot":11,"name":"Source URL","elements":{"1":{"slot":1,"values":{"1":{"slot":1,"type":"STRING","value":"hdfs://host:port/filePath"}}}},"visible":false},"12":{"slot":12,"name":"Perform Certificate Validation","elements":{"1":{"slot":1,"values":{"1":{"slot":1,"type":"STRING","value":"No"}}}},"visible":true},"13":{"slot":13,"name":"Source URL","elements":{"1":{"slot":1,"values":{"1":{"slot":1,"type":"STRING","value":"https://github.com/MatillionDeveloper/Data/raw/main/spatial/PB2002-LineString.csv.gz"}}}},"visible":true},"14":{"slot":14,"name":"Source Username","elements":{"1":{"slot":1,"values":{"1":{"slot":1,"type":"STRING","value":""}}}},"visible":true},"15":{"slot":15,"name":"Source Password","elements":{"1":{"slot":1,"values":{"1":{"slot":1,"type":"PASSWORD","value":""}}}},"visible":true},"16":{"slot":16,"name":"Source URL","elements":{"1":{"slot":1,"values":{"1":{"slot":1,"type":"STRING","value":"http://[username[:password]@]hostname[:port][absolute-path]"}}}},"visible":false},"17":{"slot":17,"name":"Source Username","elements":{"1":{"slot":1,"values":{"1":{"slot":1,"type":"STRING","value":""}}}},"visible":false},"18":{"slot":18,"name":"Source Password","elements":{"1":{"slot":1,"values":{"1":{"slot":1,"type":"PASSWORD","value":""}}}},"visible":false},"19":{"slot":19,"name":"Source URL","elements":{},"visible":false},"20":{"slot":20,"name":"Set Home Directory as Root","elements":{"1":{"slot":1,"values":{"1":{"slot":1,"type":"STRING","value":"No"}}}},"visible":false},"21":{"slot":21,"name":"Source URL","elements":{"1":{"slot":1,"values":{"1":{"slot":1,"type":"STRING","value":"sftp://[username[:password]@]hostname[:port][path]"}}}},"visible":false},"22":{"slot":22,"name":"Source Username","elements":{"1":{"slot":1,"values":{"1":{"slot":1,"type":"STRING","value":""}}}},"visible":false},"23":{"slot":23,"name":"Source Password","elements":{"1":{"slot":1,"values":{"1":{"slot":1,"type":"PASSWORD","value":""}}}},"visible":false},"24":{"slot":24,"name":"Source SFTP Key","elements":{"1":{"slot":1,"values":{"1":{"slot":1,"type":"STRING","value":""}}}},"visible":false},"25":{"slot":25,"name":"Source URL","elements":{"1":{"slot":1,"values":{"1":{"slot":1,"type":"STRING","value":"smb://[[[authdomain;]user@]host[:port][/share[/dirpath][/name]]][?context]"}}}},"visible":false},"26":{"slot":26,"name":"Source Domain","elements":{"1":{"slot":1,"values":{"1":{"slot":1,"type":"STRING","value":""}}}},"visible":false},"27":{"slot":27,"name":"Source Username","elements":{"1":{"slot":1,"values":{"1":{"slot":1,"type":"STRING","value":""}}}},"visible":false},"28":{"slot":28,"name":"Source Password","elements":{"1":{"slot":1,"values":{"1":{"slot":1,"type":"PASSWORD","value":""}}}},"visible":false},"29":{"slot":29,"name":"Target URL","elements":{},"visible":false},"30":{"slot":30,"name":"Target URL","elements":{"1":{"slot":1,"values":{"1":{"slot":1,"type":"STRING","value":"hdfs://host:port/filePath"}}}},"visible":false},"31":{"slot":31,"name":"Target URL","elements":{"1":{"slot":1,"values":{"1":{"slot":1,"type":"STRING","value":"s3://${examples_storage}"}}}},"visible":true},"33":{"slot":33,"name":"Set Home Directory as Root","elements":{"1":{"slot":1,"values":{"1":{"slot":1,"type":"STRING","value":"No"}}}},"visible":false},"34":{"slot":34,"name":"Target URL","elements":{"1":{"slot":1,"values":{"1":{"slot":1,"type":"STRING","value":"sftp://[username[:password]@]hostname[:port][path]"}}}},"visible":false},"35":{"slot":35,"name":"Target Username","elements":{"1":{"slot":1,"values":{"1":{"slot":1,"type":"STRING","value":""}}}},"visible":false},"36":{"slot":36,"name":"Target Password","elements":{"1":{"slot":1,"values":{"1":{"slot":1,"type":"PASSWORD","value":""}}}},"visible":false},"37":{"slot":37,"name":"Target SFTP Key","elements":{"1":{"slot":1,"values":{"1":{"slot":1,"type":"STRING","value":""}}}},"visible":false},"38":{"slot":38,"name":"Target URL","elements":{"1":{"slot":1,"values":{"1":{"slot":1,"type":"STRING","value":"smb://[[[authdomain;]user@]host[:port][/share[/dirpath][/name]]][?context]"}}}},"visible":false},"39":{"slot":39,"name":"Target Domain","elements":{"1":{"slot":1,"values":{"1":{"slot":1,"type":"STRING","value":""}}}},"visible":false},"40":{"slot":40,"name":"Target Username","elements":{"1":{"slot":1,"values":{"1":{"slot":1,"type":"STRING","value":""}}}},"visible":false},"41":{"slot":41,"name":"Target Password","elements":{"1":{"slot":1,"values":{"1":{"slot":1,"type":"PASSWORD","value":""}}}},"visible":false},"42":{"slot":42,"name":"Unpack ZIP file","elements":{"1":{"slot":1,"values":{"1":{"slot":1,"type":"STRING","value":"No"}}}},"visible":true},"43":{"slot":43,"name":"Gzip data","elements":{"1":{"slot":1,"values":{"1":{"slot":1,"type":"STRING","value":"No"}}}},"visible":true},"44":{"slot":44,"name":"Access Control List Options","elements":{"1":{"slot":1,"values":{"1":{"slot":1,"type":"STRING","value":""}}}},"visible":true},"50":{"slot":50,"name":"URL","elements":{"1":{"slot":1,"values":{"1":{"slot":1,"type":"STRING","value":"https://<account>.sharepoint.com"}}}},"visible":false},"51":{"slot":51,"name":"User","elements":{"1":{"slot":1,"values":{"1":{"slot":1,"type":"STRING","value":""}}}},"visible":false},"52":{"slot":52,"name":"Password","elements":{"1":{"slot":1,"values":{"1":{"slot":1,"type":"PASSWORD","value":""}}}},"visible":false},"53":{"slot":53,"name":"SharePoint Edition","elements":{"1":{"slot":1,"values":{"1":{"slot":1,"type":"STRING","value":"SharePoint Online"}}}},"visible":false},"54":{"slot":54,"name":"File Type","elements":{"1":{"slot":1,"values":{"1":{"slot":1,"type":"STRING","value":"Document"}}}},"visible":false},"55":{"slot":55,"name":"Library","elements":{"1":{"slot":1,"values":{"1":{"slot":1,"type":"STRING","value":""}}}},"visible":false},"56":{"slot":56,"name":"File URL","elements":{"1":{"slot":1,"values":{"1":{"slot":1,"type":"STRING","value":""}}}},"visible":false},"57":{"slot":57,"name":"Connection Options","elements":{},"visible":false},"90":{"slot":90,"name":"Authentication","elements":{"1":{"slot":1,"values":{"1":{"slot":1,"type":"STRING","value":""}}}},"visible":false},"91":{"slot":91,"name":"File ID","elements":{"1":{"slot":1,"values":{"1":{"slot":1,"type":"STRING","value":""}}}},"visible":false},"93":{"slot":93,"name":"File ID","elements":{"1":{"slot":1,"values":{"1":{"slot":1,"type":"STRING","value":""}}}},"visible":false},"94":{"slot":94,"name":"Path","elements":{"1":{"slot":1,"values":{"1":{"slot":1,"type":"STRING","value":""}}}},"visible":false},"95":{"slot":95,"name":"Download Format","elements":{"1":{"slot":1,"values":{"1":{"slot":1,"type":"STRING","value":"HTML"}}}},"visible":false},"96":{"slot":96,"name":"Download As Zip","elements":{"1":{"slot":1,"values":{"1":{"slot":1,"type":"STRING","value":"No"}}}},"visible":false},"97":{"slot":97,"name":"Authentication","elements":{"1":{"slot":1,"values":{"1":{"slot":1,"type":"STRING","value":""}}}},"visible":false},"98":{"slot":98,"name":"File Type","elements":{"1":{"slot":1,"values":{"1":{"slot":1,"type":"STRING","value":"File"}}}},"visible":false},"158":{"slot":158,"name":"Service Type","elements":{"1":{"slot":1,"values":{"1":{"slot":1,"type":"STRING","value":"SOAP"}}}},"visible":false},"159":{"slot":159,"name":"Authentication","elements":{"1":{"slot":1,"values":{"1":{"slot":1,"type":"STRING","value":""}}}},"visible":false},"16040":{"slot":16040,"name":"Blob Location","elements":{},"visible":false},"16140":{"slot":16140,"name":"Blob Location","elements":{},"visible":false},"40000":{"slot":40000,"name":"Encryption","elements":{"1":{"slot":1,"values":{"1":{"slot":1,"type":"STRING","value":"None"}}}},"visible":true},"40001":{"slot":40001,"name":"KMS Key ID","elements":{"1":{"slot":1,"values":{"1":{"slot":1,"type":"STRING","value":""}}}},"visible":false}},"activationStatus":"ENABLED","outputIterationConnectorIDs":[],"inputIterationConnectorIDs":[]},"4635":{"id":4635,"inputCardinality":"ONE","outputCardinality":"MANY","connectorHint":"SUCCESS_FAIL","executionHint":"EXECUTE","implementationID":620619864,"x":80,"y":64,"width":32,"height":32,"inputConnectorIDs":[4641],"outputSuccessConnectorIDs":[4695],"outputFailureConnectorIDs":[],"outputUnconditionalConnectorIDs":[],"outputTrueConnectorIDs":[],"outputFalseConnectorIDs":[],"exportMappings":{},"parameters":{"1":{"slot":1,"name":"Name","elements":{"1":{"slot":1,"values":{"1":{"slot":1,"type":"STRING","value":"Earthquakes"}}}},"visible":true},"2":{"slot":2,"name":"Source Type","elements":{"1":{"slot":1,"values":{"1":{"slot":1,"type":"STRING","value":"HTTPS"}}}},"visible":true},"4":{"slot":4,"name":"Target Object Name","elements":{"1":{"slot":1,"values":{"1":{"slot":1,"type":"STRING","value":"matillion-examples/spatial/EMSC-2018-Events.csv.gz"}}}},"visible":true},"5":{"slot":5,"name":"Target Type","elements":{"1":{"slot":1,"values":{"1":{"slot":1,"type":"STRING","value":"S3"}}}},"visible":true},"6":{"slot":6,"name":"Set Home Directory as Root","elements":{"1":{"slot":1,"values":{"1":{"slot":1,"type":"STRING","value":"No"}}}},"visible":false},"7":{"slot":7,"name":"Source URL","elements":{"1":{"slot":1,"values":{"1":{"slot":1,"type":"STRING","value":"ftp://[username[:password]@]hostname[:port][path]"}}}},"visible":false},"8":{"slot":8,"name":"Source Username","elements":{"1":{"slot":1,"values":{"1":{"slot":1,"type":"STRING","value":""}}}},"visible":false},"9":{"slot":9,"name":"Source Password","elements":{"1":{"slot":1,"values":{"1":{"slot":1,"type":"PASSWORD","value":""}}}},"visible":false},"10":{"slot":10,"name":"Source URL","elements":{},"visible":false},"11":{"slot":11,"name":"Source URL","elements":{"1":{"slot":1,"values":{"1":{"slot":1,"type":"STRING","value":"hdfs://host:port/filePath"}}}},"visible":false},"12":{"slot":12,"name":"Perform Certificate Validation","elements":{"1":{"slot":1,"values":{"1":{"slot":1,"type":"STRING","value":"No"}}}},"visible":true},"13":{"slot":13,"name":"Source URL","elements":{"1":{"slot":1,"values":{"1":{"slot":1,"type":"STRING","value":"https://github.com/MatillionDeveloper/Data/raw/main/spatial/EMSC-2018-Events.csv.gz"}}}},"visible":true},"14":{"slot":14,"name":"Source Username","elements":{"1":{"slot":1,"values":{"1":{"slot":1,"type":"STRING","value":""}}}},"visible":true},"15":{"slot":15,"name":"Source Password","elements":{"1":{"slot":1,"values":{"1":{"slot":1,"type":"PASSWORD","value":""}}}},"visible":true},"16":{"slot":16,"name":"Source URL","elements":{"1":{"slot":1,"values":{"1":{"slot":1,"type":"STRING","value":"http://[username[:password]@]hostname[:port][absolute-path]"}}}},"visible":false},"17":{"slot":17,"name":"Source Username","elements":{"1":{"slot":1,"values":{"1":{"slot":1,"type":"STRING","value":""}}}},"visible":false},"18":{"slot":18,"name":"Source Password","elements":{"1":{"slot":1,"values":{"1":{"slot":1,"type":"PASSWORD","value":""}}}},"visible":false},"19":{"slot":19,"name":"Source URL","elements":{},"visible":false},"20":{"slot":20,"name":"Set Home Directory as Root","elements":{"1":{"slot":1,"values":{"1":{"slot":1,"type":"STRING","value":"No"}}}},"visible":false},"21":{"slot":21,"name":"Source URL","elements":{"1":{"slot":1,"values":{"1":{"slot":1,"type":"STRING","value":"sftp://[username[:password]@]hostname[:port][path]"}}}},"visible":false},"22":{"slot":22,"name":"Source Username","elements":{"1":{"slot":1,"values":{"1":{"slot":1,"type":"STRING","value":""}}}},"visible":false},"23":{"slot":23,"name":"Source Password","elements":{"1":{"slot":1,"values":{"1":{"slot":1,"type":"PASSWORD","value":""}}}},"visible":false},"24":{"slot":24,"name":"Source SFTP Key","elements":{"1":{"slot":1,"values":{"1":{"slot":1,"type":"STRING","value":""}}}},"visible":false},"25":{"slot":25,"name":"Source URL","elements":{"1":{"slot":1,"values":{"1":{"slot":1,"type":"STRING","value":"smb://[[[authdomain;]user@]host[:port][/share[/dirpath][/name]]][?context]"}}}},"visible":false},"26":{"slot":26,"name":"Source Domain","elements":{"1":{"slot":1,"values":{"1":{"slot":1,"type":"STRING","value":""}}}},"visible":false},"27":{"slot":27,"name":"Source Username","elements":{"1":{"slot":1,"values":{"1":{"slot":1,"type":"STRING","value":""}}}},"visible":false},"28":{"slot":28,"name":"Source Password","elements":{"1":{"slot":1,"values":{"1":{"slot":1,"type":"PASSWORD","value":""}}}},"visible":false},"29":{"slot":29,"name":"Target URL","elements":{},"visible":false},"30":{"slot":30,"name":"Target URL","elements":{"1":{"slot":1,"values":{"1":{"slot":1,"type":"STRING","value":"hdfs://host:port/filePath"}}}},"visible":false},"31":{"slot":31,"name":"Target URL","elements":{"1":{"slot":1,"values":{"1":{"slot":1,"type":"STRING","value":"s3://${examples_storage}"}}}},"visible":true},"33":{"slot":33,"name":"Set Home Directory as Root","elements":{"1":{"slot":1,"values":{"1":{"slot":1,"type":"STRING","value":"No"}}}},"visible":false},"34":{"slot":34,"name":"Target URL","elements":{"1":{"slot":1,"values":{"1":{"slot":1,"type":"STRING","value":"sftp://[username[:password]@]hostname[:port][path]"}}}},"visible":false},"35":{"slot":35,"name":"Target Username","elements":{"1":{"slot":1,"values":{"1":{"slot":1,"type":"STRING","value":""}}}},"visible":false},"36":{"slot":36,"name":"Target Password","elements":{"1":{"slot":1,"values":{"1":{"slot":1,"type":"PASSWORD","value":""}}}},"visible":false},"37":{"slot":37,"name":"Target SFTP Key","elements":{"1":{"slot":1,"values":{"1":{"slot":1,"type":"STRING","value":""}}}},"visible":false},"38":{"slot":38,"name":"Target URL","elements":{"1":{"slot":1,"values":{"1":{"slot":1,"type":"STRING","value":"smb://[[[authdomain;]user@]host[:port][/share[/dirpath][/name]]][?context]"}}}},"visible":false},"39":{"slot":39,"name":"Target Domain","elements":{"1":{"slot":1,"values":{"1":{"slot":1,"type":"STRING","value":""}}}},"visible":false},"40":{"slot":40,"name":"Target Username","elements":{"1":{"slot":1,"values":{"1":{"slot":1,"type":"STRING","value":""}}}},"visible":false},"41":{"slot":41,"name":"Target Password","elements":{"1":{"slot":1,"values":{"1":{"slot":1,"type":"PASSWORD","value":""}}}},"visible":false},"42":{"slot":42,"name":"Unpack ZIP file","elements":{"1":{"slot":1,"values":{"1":{"slot":1,"type":"STRING","value":"No"}}}},"visible":true},"43":{"slot":43,"name":"Gzip data","elements":{"1":{"slot":1,"values":{"1":{"slot":1,"type":"STRING","value":"No"}}}},"visible":true},"44":{"slot":44,"name":"Access Control List Options","elements":{"1":{"slot":1,"values":{"1":{"slot":1,"type":"STRING","value":""}}}},"visible":true},"50":{"slot":50,"name":"URL","elements":{"1":{"slot":1,"values":{"1":{"slot":1,"type":"STRING","value":"https://<account>.sharepoint.com"}}}},"visible":false},"51":{"slot":51,"name":"User","elements":{"1":{"slot":1,"values":{"1":{"slot":1,"type":"STRING","value":""}}}},"visible":false},"52":{"slot":52,"name":"Password","elements":{"1":{"slot":1,"values":{"1":{"slot":1,"type":"PASSWORD","value":""}}}},"visible":false},"53":{"slot":53,"name":"SharePoint Edition","elements":{"1":{"slot":1,"values":{"1":{"slot":1,"type":"STRING","value":"SharePoint Online"}}}},"visible":false},"54":{"slot":54,"name":"File Type","elements":{"1":{"slot":1,"values":{"1":{"slot":1,"type":"STRING","value":"Document"}}}},"visible":false},"55":{"slot":55,"name":"Library","elements":{"1":{"slot":1,"values":{"1":{"slot":1,"type":"STRING","value":""}}}},"visible":false},"56":{"slot":56,"name":"File URL","elements":{"1":{"slot":1,"values":{"1":{"slot":1,"type":"STRING","value":""}}}},"visible":false},"57":{"slot":57,"name":"Connection Options","elements":{},"visible":false},"90":{"slot":90,"name":"Authentication","elements":{"1":{"slot":1,"values":{"1":{"slot":1,"type":"STRING","value":""}}}},"visible":false},"91":{"slot":91,"name":"File ID","elements":{"1":{"slot":1,"values":{"1":{"slot":1,"type":"STRING","value":""}}}},"visible":false},"93":{"slot":93,"name":"File ID","elements":{"1":{"slot":1,"values":{"1":{"slot":1,"type":"STRING","value":""}}}},"visible":false},"94":{"slot":94,"name":"Path","elements":{"1":{"slot":1,"values":{"1":{"slot":1,"type":"STRING","value":""}}}},"visible":false},"95":{"slot":95,"name":"Download Format","elements":{"1":{"slot":1,"values":{"1":{"slot":1,"type":"STRING","value":"HTML"}}}},"visible":false},"96":{"slot":96,"name":"Download As Zip","elements":{"1":{"slot":1,"values":{"1":{"slot":1,"type":"STRING","value":"No"}}}},"visible":false},"97":{"slot":97,"name":"Authentication","elements":{"1":{"slot":1,"values":{"1":{"slot":1,"type":"STRING","value":""}}}},"visible":false},"98":{"slot":98,"name":"File Type","elements":{"1":{"slot":1,"values":{"1":{"slot":1,"type":"STRING","value":"File"}}}},"visible":false},"158":{"slot":158,"name":"Service Type","elements":{"1":{"slot":1,"values":{"1":{"slot":1,"type":"STRING","value":"SOAP"}}}},"visible":false},"159":{"slot":159,"name":"Authentication","elements":{"1":{"slot":1,"values":{"1":{"slot":1,"type":"STRING","value":""}}}},"visible":false},"16040":{"slot":16040,"name":"Blob Location","elements":{},"visible":false},"16140":{"slot":16140,"name":"Blob Location","elements":{},"visible":false},"40000":{"slot":40000,"name":"Encryption","elements":{"1":{"slot":1,"values":{"1":{"slot":1,"type":"STRING","value":"None"}}}},"visible":true},"40001":{"slot":40001,"name":"KMS Key ID","elements":{"1":{"slot":1,"values":{"1":{"slot":1,"type":"STRING","value":""}}}},"visible":false}},"activationStatus":"ENABLED","outputIterationConnectorIDs":[],"inputIterationConnectorIDs":[]},"4688":{"id":4688,"inputCardinality":"ONE","outputCardinality":"MANY","connectorHint":"SUCCESS_FAIL","executionHint":"EXECUTE","implementationID":-798585337,"x":256,"y":-64,"width":32,"height":32,"inputConnectorIDs":[4689],"outputSuccessConnectorIDs":[4760],"outputFailureConnectorIDs":[],"outputUnconditionalConnectorIDs":[],"outputTrueConnectorIDs":[],"outputFalseConnectorIDs":[],"exportMappings":{},"parameters":{"1":{"slot":1,"name":"Name","elements":{"1":{"slot":1,"values":{"1":{"slot":1,"type":"STRING","value":"stg_pb2002"}}}},"visible":true},"2":{"slot":2,"name":"SQL Script","elements":{"1":{"slot":1,"values":{"1":{"slot":1,"type":"STRING","value":"CREATE OR REPLACE TABLE \"${examples_schema}\".\"stg_pb2002\" (\n\t\"id\"   VARCHAR(20),\n\t\"name\" VARCHAR(20),\n\t\"type\" VARCHAR(20),\n\t\"geo\" GEOGRAPHY\n)"}}}},"visible":true}},"activationStatus":"ENABLED","outputIterationConnectorIDs":[],"inputIterationConnectorIDs":[]},"4694":{"id":4694,"inputCardinality":"ONE","outputCardinality":"MANY","connectorHint":"SUCCESS_FAIL","executionHint":"EXECUTE","implementationID":-798585337,"x":256,"y":64,"width":32,"height":32,"inputConnectorIDs":[4695],"outputSuccessConnectorIDs":[4821],"outputFailureConnectorIDs":[],"outputUnconditionalConnectorIDs":[],"outputTrueConnectorIDs":[],"outputFalseConnectorIDs":[],"exportMappings":{},"parameters":{"1":{"slot":1,"name":"Name","elements":{"1":{"slot":1,"values":{"1":{"slot":1,"type":"STRING","value":"stg_quakes"}}}},"visible":true},"2":{"slot":2,"name":"SQL Script","elements":{"1":{"slot":1,"values":{"1":{"slot":1,"type":"STRING","value":"CREATE OR REPLACE TABLE \"${examples_schema}\".\"stg_quakes\" (\n\t\"ID\" VARCHAR(40) NOT NULL,\n\t\"UTC\" VARCHAR(40) NOT NULL,\n\t\"depth\" FLOAT NOT NULL,\n\t\"magnitude\" FLOAT NOT NULL,\n\t\"geo\" GEOGRAPHY NOT NULL\n)"}}}},"visible":true}},"activationStatus":"ENABLED","outputIterationConnectorIDs":[],"inputIterationConnectorIDs":[]},"4759":{"id":4759,"inputCardinality":"ONE","outputCardinality":"MANY","connectorHint":"SUCCESS_FAIL","executionHint":"EXECUTE","implementationID":773867971,"x":432,"y":-64,"width":32,"height":32,"inputConnectorIDs":[4760],"outputSuccessConnectorIDs":[4874],"outputFailureConnectorIDs":[],"outputUnconditionalConnectorIDs":[],"outputTrueConnectorIDs":[],"outputFalseConnectorIDs":[],"exportMappings":{},"parameters":{"1":{"slot":1,"name":"Name","elements":{"1":{"slot":1,"values":{"1":{"slot":1,"type":"STRING","value":"Load PB2002"}}}},"visible":true},"4":{"slot":4,"name":"S3 Object Prefix","elements":{"1":{"slot":1,"values":{"1":{"slot":1,"type":"STRING","value":"s3://${examples_storage}"}}}},"visible":true},"5":{"slot":5,"name":"Warehouse","elements":{"1":{"slot":1,"values":{"1":{"slot":1,"type":"STRING","value":"[Environment Default]"}}}},"visible":true},"6":{"slot":6,"name":"Database","elements":{"1":{"slot":1,"values":{"1":{"slot":1,"type":"STRING","value":"[Environment Default]"}}}},"visible":true},"7":{"slot":7,"name":"Schema","elements":{"1":{"slot":1,"values":{"1":{"slot":1,"type":"STRING","value":"${examples_schema}"}}}},"visible":true},"8":{"slot":8,"name":"Target Table","elements":{"1":{"slot":1,"values":{"1":{"slot":1,"type":"STRING","value":"stg_pb2002"}}}},"visible":true},"9":{"slot":9,"name":"Load Columns","elements":{},"visible":true},"10":{"slot":10,"name":"Format","elements":{"1":{"slot":1,"values":{"1":{"slot":1,"type":"STRING","value":"[Custom]"}}}},"visible":true},"11":{"slot":11,"name":"File Type","elements":{"1":{"slot":1,"values":{"1":{"slot":1,"type":"STRING","value":"CSV"}}}},"visible":true},"12":{"slot":12,"name":"Compression","elements":{"1":{"slot":1,"values":{"1":{"slot":1,"type":"STRING","value":"AUTO"}}}},"visible":true},"20":{"slot":20,"name":"Record Delimiter","elements":{"1":{"slot":1,"values":{"1":{"slot":1,"type":"STRING","value":""}}}},"visible":true},"21":{"slot":21,"name":"Field Delimiter","elements":{"1":{"slot":1,"values":{"1":{"slot":1,"type":"STRING","value":"|"}}}},"visible":true},"22":{"slot":22,"name":"Skip Header","elements":{"1":{"slot":1,"values":{"1":{"slot":1,"type":"INTEGER","value":""}}}},"visible":true},"23":{"slot":23,"name":"Date Format","elements":{"1":{"slot":1,"values":{"1":{"slot":1,"type":"STRING","value":""}}}},"visible":true},"24":{"slot":24,"name":"Time Format","elements":{"1":{"slot":1,"values":{"1":{"slot":1,"type":"STRING","value":""}}}},"visible":true},"25":{"slot":25,"name":"Timestamp Format","elements":{"1":{"slot":1,"values":{"1":{"slot":1,"type":"STRING","value":""}}}},"visible":true},"26":{"slot":26,"name":"","elements":{},"visible":false},"27":{"slot":27,"name":"Escape","elements":{"1":{"slot":1,"values":{"1":{"slot":1,"type":"CHAR_OR_ESCAPE_SEQUENCE","value":""}}}},"visible":true},"28":{"slot":28,"name":"Escape Unenclosed Field","elements":{"1":{"slot":1,"values":{"1":{"slot":1,"type":"CHAR_OR_ESCAPE_SEQUENCE","value":""}}}},"visible":true},"29":{"slot":29,"name":"Trim Space","elements":{"1":{"slot":1,"values":{"1":{"slot":1,"type":"STRING","value":"False"}}}},"visible":true},"30":{"slot":30,"name":"Field Optionally Enclosed","elements":{"1":{"slot":1,"values":{"1":{"slot":1,"type":"CHAR","value":""}}}},"visible":true},"31":{"slot":31,"name":"Null If","elements":{},"visible":true},"32":{"slot":32,"name":"Error On Column Count Mismatch","elements":{"1":{"slot":1,"values":{"1":{"slot":1,"type":"STRING","value":"False"}}}},"visible":true},"33":{"slot":33,"name":"Empty Field as Null","elements":{"1":{"slot":1,"values":{"1":{"slot":1,"type":"STRING","value":"True"}}}},"visible":true},"34":{"slot":34,"name":"Encoding Type","elements":{"1":{"slot":1,"values":{"1":{"slot":1,"type":"STRING","value":""}}}},"visible":true},"35":{"slot":35,"name":"Skip Blank Lines","elements":{"1":{"slot":1,"values":{"1":{"slot":1,"type":"STRING","value":"False"}}}},"visible":true},"36":{"slot":36,"name":"Replace Invalid Characters","elements":{"1":{"slot":1,"values":{"1":{"slot":1,"type":"STRING","value":"False"}}}},"visible":true},"40":{"slot":40,"name":"Enable Octal","elements":{"1":{"slot":1,"values":{"1":{"slot":1,"type":"STRING","value":"False"}}}},"visible":false},"41":{"slot":41,"name":"Allow Duplicates","elements":{"1":{"slot":1,"values":{"1":{"slot":1,"type":"STRING","value":"False"}}}},"visible":false},"42":{"slot":42,"name":"Strip Outer Array","elements":{"1":{"slot":1,"values":{"1":{"slot":1,"type":"STRING","value":"False"}}}},"visible":false},"43":{"slot":43,"name":"Strip Null Values","elements":{"1":{"slot":1,"values":{"1":{"slot":1,"type":"STRING","value":"False"}}}},"visible":false},"44":{"slot":44,"name":"Ignore UTF8 Errors","elements":{"1":{"slot":1,"values":{"1":{"slot":1,"type":"STRING","value":"False"}}}},"visible":false},"45":{"slot":45,"name":"Nest Columns","elements":{"1":{"slot":1,"values":{"1":{"slot":1,"type":"STRING","value":"False"}}}},"visible":false},"46":{"slot":46,"name":"Null If","elements":{},"visible":false},"47":{"slot":47,"name":"Trim Space","elements":{"1":{"slot":1,"values":{"1":{"slot":1,"type":"STRING","value":"False"}}}},"visible":false},"50":{"slot":50,"name":"Null If","elements":{},"visible":false},"51":{"slot":51,"name":"Trim Space","elements":{"1":{"slot":1,"values":{"1":{"slot":1,"type":"STRING","value":"False"}}}},"visible":false},"60":{"slot":60,"name":"Ignore UTF8 Errors","elements":{"1":{"slot":1,"values":{"1":{"slot":1,"type":"STRING","value":"False"}}}},"visible":false},"61":{"slot":61,"name":"Preserve Space","elements":{"1":{"slot":1,"values":{"1":{"slot":1,"type":"STRING","value":"False"}}}},"visible":false},"62":{"slot":62,"name":"Strip Outer Element","elements":{"1":{"slot":1,"values":{"1":{"slot":1,"type":"STRING","value":"False"}}}},"visible":false},"63":{"slot":63,"name":"Disable Snowflake Data","elements":{"1":{"slot":1,"values":{"1":{"slot":1,"type":"STRING","value":"False"}}}},"visible":false},"64":{"slot":64,"name":"Disable Auto Convert","elements":{"1":{"slot":1,"values":{"1":{"slot":1,"type":"STRING","value":"False"}}}},"visible":false},"66":{"slot":66,"name":"Null If","elements":{},"visible":false},"67":{"slot":67,"name":"Trim Space","elements":{"1":{"slot":1,"values":{"1":{"slot":1,"type":"STRING","value":"False"}}}},"visible":false},"70":{"slot":70,"name":"Null If","elements":{},"visible":false},"71":{"slot":71,"name":"Trim Space","elements":{"1":{"slot":1,"values":{"1":{"slot":1,"type":"STRING","value":"False"}}}},"visible":false},"120":{"slot":120,"name":"On Error","elements":{"1":{"slot":1,"values":{"1":{"slot":1,"type":"STRING","value":"Abort Statement"}}}},"visible":true},"121":{"slot":121,"name":"n","elements":{"1":{"slot":1,"values":{"1":{"slot":1,"type":"INTEGER","value":""}}}},"visible":false},"122":{"slot":122,"name":"Size Limit (B)","elements":{"1":{"slot":1,"values":{"1":{"slot":1,"type":"INTEGER","value":""}}}},"visible":true},"123":{"slot":123,"name":"Purge Files","elements":{"1":{"slot":1,"values":{"1":{"slot":1,"type":"STRING","value":"False"}}}},"visible":true},"124":{"slot":124,"name":"Truncate Columns","elements":{"1":{"slot":1,"values":{"1":{"slot":1,"type":"STRING","value":"False"}}}},"visible":true},"125":{"slot":125,"name":"Force Load","elements":{"1":{"slot":1,"values":{"1":{"slot":1,"type":"STRING","value":"True"}}}},"visible":true},"126":{"slot":126,"name":"Match By Column Name","elements":{"1":{"slot":1,"values":{"1":{"slot":1,"type":"STRING","value":"None"}}}},"visible":false},"140":{"slot":140,"name":"Encryption","elements":{"1":{"slot":1,"values":{"1":{"slot":1,"type":"STRING","value":"None"}}}},"visible":true},"141":{"slot":141,"name":"Master Key","elements":{"1":{"slot":1,"values":{"1":{"slot":1,"type":"STRING","value":""}}}},"visible":false},"142":{"slot":142,"name":"KMS Key Id","elements":{"1":{"slot":1,"values":{"1":{"slot":1,"type":"STRING","value":""}}}},"visible":false},"200":{"slot":200,"name":"Stage","elements":{"1":{"slot":1,"values":{"1":{"slot":1,"type":"STRING","value":"[Custom]"}}}},"visible":true},"201":{"slot":201,"name":"Pattern","elements":{"1":{"slot":1,"values":{"1":{"slot":1,"type":"STRING","value":"matillion-examples/spatial/PB2002-LineString.csv.gz"}}}},"visible":true},"203":{"slot":203,"name":"Metadata Fields","elements":{},"visible":false}},"activationStatus":"ENABLED","outputIterationConnectorIDs":[],"inputIterationConnectorIDs":[]},"4815":{"id":4815,"inputCardinality":"ONE","outputCardinality":"MANY","connectorHint":"SUCCESS_FAIL","executionHint":"EXECUTE","implementationID":773867971,"x":432,"y":64,"width":32,"height":32,"inputConnectorIDs":[4821],"outputSuccessConnectorIDs":[4880],"outputFailureConnectorIDs":[],"outputUnconditionalConnectorIDs":[],"outputTrueConnectorIDs":[],"outputFalseConnectorIDs":[],"exportMappings":{},"parameters":{"1":{"slot":1,"name":"Name","elements":{"1":{"slot":1,"values":{"1":{"slot":1,"type":"STRING","value":"Load Earthquakes"}}}},"visible":true},"4":{"slot":4,"name":"S3 Object Prefix","elements":{"1":{"slot":1,"values":{"1":{"slot":1,"type":"STRING","value":"s3://${examples_storage}"}}}},"visible":true},"5":{"slot":5,"name":"Warehouse","elements":{"1":{"slot":1,"values":{"1":{"slot":1,"type":"STRING","value":"[Environment Default]"}}}},"visible":true},"6":{"slot":6,"name":"Database","elements":{"1":{"slot":1,"values":{"1":{"slot":1,"type":"STRING","value":"[Environment Default]"}}}},"visible":true},"7":{"slot":7,"name":"Schema","elements":{"1":{"slot":1,"values":{"1":{"slot":1,"type":"STRING","value":"${examples_schema}"}}}},"visible":true},"8":{"slot":8,"name":"Target Table","elements":{"1":{"slot":1,"values":{"1":{"slot":1,"type":"STRING","value":"stg_quakes"}}}},"visible":true},"9":{"slot":9,"name":"Load Columns","elements":{},"visible":true},"10":{"slot":10,"name":"Format","elements":{"1":{"slot":1,"values":{"1":{"slot":1,"type":"STRING","value":"[Custom]"}}}},"visible":true},"11":{"slot":11,"name":"File Type","elements":{"1":{"slot":1,"values":{"1":{"slot":1,"type":"STRING","value":"CSV"}}}},"visible":true},"12":{"slot":12,"name":"Compression","elements":{"1":{"slot":1,"values":{"1":{"slot":1,"type":"STRING","value":"AUTO"}}}},"visible":true},"20":{"slot":20,"name":"Record Delimiter","elements":{"1":{"slot":1,"values":{"1":{"slot":1,"type":"STRING","value":""}}}},"visible":true},"21":{"slot":21,"name":"Field Delimiter","elements":{"1":{"slot":1,"values":{"1":{"slot":1,"type":"STRING","value":"|"}}}},"visible":true},"22":{"slot":22,"name":"Skip Header","elements":{"1":{"slot":1,"values":{"1":{"slot":1,"type":"STRING","value":"1"}}}},"visible":true},"23":{"slot":23,"name":"Date Format","elements":{"1":{"slot":1,"values":{"1":{"slot":1,"type":"STRING","value":""}}}},"visible":true},"24":{"slot":24,"name":"Time Format","elements":{"1":{"slot":1,"values":{"1":{"slot":1,"type":"STRING","value":""}}}},"visible":true},"25":{"slot":25,"name":"Timestamp Format","elements":{"1":{"slot":1,"values":{"1":{"slot":1,"type":"STRING","value":""}}}},"visible":true},"26":{"slot":26,"name":"","elements":{},"visible":false},"27":{"slot":27,"name":"Escape","elements":{"1":{"slot":1,"values":{"1":{"slot":1,"type":"CHAR_OR_ESCAPE_SEQUENCE","value":""}}}},"visible":true},"28":{"slot":28,"name":"Escape Unenclosed Field","elements":{"1":{"slot":1,"values":{"1":{"slot":1,"type":"CHAR_OR_ESCAPE_SEQUENCE","value":""}}}},"visible":true},"29":{"slot":29,"name":"Trim Space","elements":{"1":{"slot":1,"values":{"1":{"slot":1,"type":"STRING","value":"False"}}}},"visible":true},"30":{"slot":30,"name":"Field Optionally Enclosed","elements":{"1":{"slot":1,"values":{"1":{"slot":1,"type":"CHAR","value":""}}}},"visible":true},"31":{"slot":31,"name":"Null If","elements":{},"visible":true},"32":{"slot":32,"name":"Error On Column Count Mismatch","elements":{"1":{"slot":1,"values":{"1":{"slot":1,"type":"STRING","value":"False"}}}},"visible":true},"33":{"slot":33,"name":"Empty Field as Null","elements":{"1":{"slot":1,"values":{"1":{"slot":1,"type":"STRING","value":"True"}}}},"visible":true},"34":{"slot":34,"name":"Encoding Type","elements":{"1":{"slot":1,"values":{"1":{"slot":1,"type":"STRING","value":""}}}},"visible":true},"35":{"slot":35,"name":"Skip Blank Lines","elements":{"1":{"slot":1,"values":{"1":{"slot":1,"type":"STRING","value":"False"}}}},"visible":true},"36":{"slot":36,"name":"Replace Invalid Characters","elements":{"1":{"slot":1,"values":{"1":{"slot":1,"type":"STRING","value":"False"}}}},"visible":true},"40":{"slot":40,"name":"Enable Octal","elements":{"1":{"slot":1,"values":{"1":{"slot":1,"type":"STRING","value":"False"}}}},"visible":false},"41":{"slot":41,"name":"Allow Duplicates","elements":{"1":{"slot":1,"values":{"1":{"slot":1,"type":"STRING","value":"False"}}}},"visible":false},"42":{"slot":42,"name":"Strip Outer Array","elements":{"1":{"slot":1,"values":{"1":{"slot":1,"type":"STRING","value":"False"}}}},"visible":false},"43":{"slot":43,"name":"Strip Null Values","elements":{"1":{"slot":1,"values":{"1":{"slot":1,"type":"STRING","value":"False"}}}},"visible":false},"44":{"slot":44,"name":"Ignore UTF8 Errors","elements":{"1":{"slot":1,"values":{"1":{"slot":1,"type":"STRING","value":"False"}}}},"visible":false},"45":{"slot":45,"name":"Nest Columns","elements":{"1":{"slot":1,"values":{"1":{"slot":1,"type":"STRING","value":"False"}}}},"visible":false},"46":{"slot":46,"name":"Null If","elements":{},"visible":false},"47":{"slot":47,"name":"Trim Space","elements":{"1":{"slot":1,"values":{"1":{"slot":1,"type":"STRING","value":"False"}}}},"visible":false},"50":{"slot":50,"name":"Null If","elements":{},"visible":false},"51":{"slot":51,"name":"Trim Space","elements":{"1":{"slot":1,"values":{"1":{"slot":1,"type":"STRING","value":"False"}}}},"visible":false},"60":{"slot":60,"name":"Ignore UTF8 Errors","elements":{"1":{"slot":1,"values":{"1":{"slot":1,"type":"STRING","value":"False"}}}},"visible":false},"61":{"slot":61,"name":"Preserve Space","elements":{"1":{"slot":1,"values":{"1":{"slot":1,"type":"STRING","value":"False"}}}},"visible":false},"62":{"slot":62,"name":"Strip Outer Element","elements":{"1":{"slot":1,"values":{"1":{"slot":1,"type":"STRING","value":"False"}}}},"visible":false},"63":{"slot":63,"name":"Disable Snowflake Data","elements":{"1":{"slot":1,"values":{"1":{"slot":1,"type":"STRING","value":"False"}}}},"visible":false},"64":{"slot":64,"name":"Disable Auto Convert","elements":{"1":{"slot":1,"values":{"1":{"slot":1,"type":"STRING","value":"False"}}}},"visible":false},"66":{"slot":66,"name":"Null If","elements":{},"visible":false},"67":{"slot":67,"name":"Trim Space","elements":{"1":{"slot":1,"values":{"1":{"slot":1,"type":"STRING","value":"False"}}}},"visible":false},"70":{"slot":70,"name":"Null If","elements":{},"visible":false},"71":{"slot":71,"name":"Trim Space","elements":{"1":{"slot":1,"values":{"1":{"slot":1,"type":"STRING","value":"False"}}}},"visible":false},"120":{"slot":120,"name":"On Error","elements":{"1":{"slot":1,"values":{"1":{"slot":1,"type":"STRING","value":"Abort Statement"}}}},"visible":true},"121":{"slot":121,"name":"n","elements":{"1":{"slot":1,"values":{"1":{"slot":1,"type":"INTEGER","value":""}}}},"visible":false},"122":{"slot":122,"name":"Size Limit (B)","elements":{"1":{"slot":1,"values":{"1":{"slot":1,"type":"INTEGER","value":""}}}},"visible":true},"123":{"slot":123,"name":"Purge Files","elements":{"1":{"slot":1,"values":{"1":{"slot":1,"type":"STRING","value":"False"}}}},"visible":true},"124":{"slot":124,"name":"Truncate Columns","elements":{"1":{"slot":1,"values":{"1":{"slot":1,"type":"STRING","value":"False"}}}},"visible":true},"125":{"slot":125,"name":"Force Load","elements":{"1":{"slot":1,"values":{"1":{"slot":1,"type":"STRING","value":"True"}}}},"visible":true},"126":{"slot":126,"name":"Match By Column Name","elements":{"1":{"slot":1,"values":{"1":{"slot":1,"type":"STRING","value":"None"}}}},"visible":false},"140":{"slot":140,"name":"Encryption","elements":{"1":{"slot":1,"values":{"1":{"slot":1,"type":"STRING","value":"None"}}}},"visible":true},"141":{"slot":141,"name":"Master Key","elements":{"1":{"slot":1,"values":{"1":{"slot":1,"type":"STRING","value":""}}}},"visible":false},"142":{"slot":142,"name":"KMS Key Id","elements":{"1":{"slot":1,"values":{"1":{"slot":1,"type":"STRING","value":""}}}},"visible":false},"200":{"slot":200,"name":"Stage","elements":{"1":{"slot":1,"values":{"1":{"slot":1,"type":"STRING","value":"[Custom]"}}}},"visible":true},"201":{"slot":201,"name":"Pattern","elements":{"1":{"slot":1,"values":{"1":{"slot":1,"type":"STRING","value":"matillion-examples/spatial/EMSC-2018-Events.csv.gz"}}}},"visible":true},"203":{"slot":203,"name":"Metadata Fields","elements":{},"visible":false}},"activationStatus":"ENABLED","outputIterationConnectorIDs":[],"inputIterationConnectorIDs":[]},"4873":{"id":4873,"inputCardinality":"MANY","outputCardinality":"MANY","connectorHint":"UNCONDITIONAL","executionHint":"FLOW","implementationID":235671163,"x":608,"y":0,"width":32,"height":32,"inputConnectorIDs":[4880,4874],"outputSuccessConnectorIDs":[],"outputFailureConnectorIDs":[],"outputUnconditionalConnectorIDs":[5037],"outputTrueConnectorIDs":[],"outputFalseConnectorIDs":[],"exportMappings":{},"parameters":{"1":{"slot":1,"name":"Name","elements":{"1":{"slot":1,"values":{"1":{"slot":1,"type":"STRING","value":"And 0"}}}},"visible":true}},"activationStatus":"ENABLED","outputIterationConnectorIDs":[],"inputIterationConnectorIDs":[]},"5036":{"id":5036,"inputCardinality":"ONE","outputCardinality":"MANY","connectorHint":"SUCCESS_FAIL","executionHint":"TRANSFORM","implementationID":1896325668,"x":720,"y":0,"width":32,"height":32,"inputConnectorIDs":[5037],"outputSuccessConnectorIDs":[5052],"outputFailureConnectorIDs":[],"outputUnconditionalConnectorIDs":[],"outputTrueConnectorIDs":[],"outputFalseConnectorIDs":[],"exportMappings":{},"parameters":{"1":{"slot":1,"name":"Name","elements":{"1":{"slot":1,"values":{"1":{"slot":1,"type":"STRING","value":"PB2002 xform"}}}},"visible":true},"2":{"slot":2,"name":"Transformation Job","elements":{"1":{"slot":1,"values":{"1":{"slot":1,"type":"STRING","value":"example PB2002 transformation"}}}},"visible":true},"3":{"slot":3,"name":"","elements":{},"visible":false},"4":{"slot":4,"name":"Set Scalar Variables","elements":{},"visible":true},"5":{"slot":5,"name":"Set Grid Variables","elements":{},"visible":true}},"activationStatus":"ENABLED","outputIterationConnectorIDs":[],"inputIterationConnectorIDs":[]},"5051":{"id":5051,"inputCardinality":"ONE","outputCardinality":"MANY","connectorHint":"SUCCESS_FAIL","executionHint":"EXECUTE","implementationID":374945314,"x":880,"y":0,"width":32,"height":32,"inputConnectorIDs":[5052],"outputSuccessConnectorIDs":[],"outputFailureConnectorIDs":[],"outputUnconditionalConnectorIDs":[],"outputTrueConnectorIDs":[],"outputFalseConnectorIDs":[],"exportMappings":{},"parameters":{"1":{"slot":1,"name":"Name","elements":{"1":{"slot":1,"values":{"1":{"slot":1,"type":"STRING","value":"S3 Unload 0"}}}},"visible":true},"4":{"slot":4,"name":"S3 Object Prefix","elements":{"1":{"slot":1,"values":{"1":{"slot":1,"type":"STRING","value":"s3://${examples_storage}"}}}},"visible":true},"5":{"slot":5,"name":"Warehouse","elements":{"1":{"slot":1,"values":{"1":{"slot":1,"type":"STRING","value":"[Environment Default]"}}}},"visible":true},"6":{"slot":6,"name":"Database","elements":{"1":{"slot":1,"values":{"1":{"slot":1,"type":"STRING","value":"[Environment Default]"}}}},"visible":true},"7":{"slot":7,"name":"Schema","elements":{"1":{"slot":1,"values":{"1":{"slot":1,"type":"STRING","value":"${examples_schema}"}}}},"visible":true},"8":{"slot":8,"name":"Target Table","elements":{"1":{"slot":1,"values":{"1":{"slot":1,"type":"STRING","value":"agg_qb"}}}},"visible":true},"10":{"slot":10,"name":"Format","elements":{"1":{"slot":1,"values":{"1":{"slot":1,"type":"STRING","value":"[Custom]"}}}},"visible":true},"11":{"slot":11,"name":"File Type","elements":{"1":{"slot":1,"values":{"1":{"slot":1,"type":"STRING","value":"CSV"}}}},"visible":true},"12":{"slot":12,"name":"Compression","elements":{"1":{"slot":1,"values":{"1":{"slot":1,"type":"STRING","value":"AUTO"}}}},"visible":true},"20":{"slot":20,"name":"Record Delimiter","elements":{"1":{"slot":1,"values":{"1":{"slot":1,"type":"STRING","value":""}}}},"visible":true},"21":{"slot":21,"name":"Field Delimiter","elements":{"1":{"slot":1,"values":{"1":{"slot":1,"type":"STRING","value":""}}}},"visible":true},"23":{"slot":23,"name":"Date Format","elements":{"1":{"slot":1,"values":{"1":{"slot":1,"type":"STRING","value":""}}}},"visible":true},"24":{"slot":24,"name":"Time Format","elements":{"1":{"slot":1,"values":{"1":{"slot":1,"type":"STRING","value":""}}}},"visible":true},"25":{"slot":25,"name":"Timestamp Format","elements":{"1":{"slot":1,"values":{"1":{"slot":1,"type":"STRING","value":""}}}},"visible":true},"26":{"slot":26,"name":"","elements":{},"visible":false},"27":{"slot":27,"name":"Escape","elements":{"1":{"slot":1,"values":{"1":{"slot":1,"type":"CHAR_OR_ESCAPE_SEQUENCE","value":""}}}},"visible":true},"28":{"slot":28,"name":"Escape Unenclosed Field","elements":{"1":{"slot":1,"values":{"1":{"slot":1,"type":"CHAR_OR_ESCAPE_SEQUENCE","value":""}}}},"visible":true},"30":{"slot":30,"name":"Field Optionally Enclosed","elements":{"1":{"slot":1,"values":{"1":{"slot":1,"type":"CHAR","value":""}}}},"visible":true},"31":{"slot":31,"name":"Null If","elements":{},"visible":true},"40":{"slot":40,"name":"Enable Octal","elements":{"1":{"slot":1,"values":{"1":{"slot":1,"type":"STRING","value":"False"}}}},"visible":false},"41":{"slot":41,"name":"Allow Duplicates","elements":{"1":{"slot":1,"values":{"1":{"slot":1,"type":"STRING","value":"False"}}}},"visible":false},"42":{"slot":42,"name":"Strip Outer Array","elements":{"1":{"slot":1,"values":{"1":{"slot":1,"type":"STRING","value":"False"}}}},"visible":false},"43":{"slot":43,"name":"Strip Null Values","elements":{"1":{"slot":1,"values":{"1":{"slot":1,"type":"STRING","value":"False"}}}},"visible":false},"44":{"slot":44,"name":"Ignore UTF8 Errors","elements":{"1":{"slot":1,"values":{"1":{"slot":1,"type":"STRING","value":"False"}}}},"visible":false},"45":{"slot":45,"name":"Nest Columns","elements":{"1":{"slot":1,"values":{"1":{"slot":1,"type":"STRING","value":"False"}}}},"visible":false},"46":{"slot":46,"name":"Null If","elements":{},"visible":false},"47":{"slot":47,"name":"Trim Space","elements":{"1":{"slot":1,"values":{"1":{"slot":1,"type":"STRING","value":"False"}}}},"visible":false},"50":{"slot":50,"name":"Null If","elements":{},"visible":false},"51":{"slot":51,"name":"Trim Space","elements":{"1":{"slot":1,"values":{"1":{"slot":1,"type":"STRING","value":"False"}}}},"visible":false},"65":{"slot":65,"name":"","elements":{},"visible":false},"66":{"slot":66,"name":"Null If","elements":{},"visible":false},"67":{"slot":67,"name":"Trim Space","elements":{"1":{"slot":1,"values":{"1":{"slot":1,"type":"STRING","value":"False"}}}},"visible":false},"70":{"slot":70,"name":"Null If","elements":{},"visible":false},"71":{"slot":71,"name":"Trim Space","elements":{"1":{"slot":1,"values":{"1":{"slot":1,"type":"STRING","value":"False"}}}},"visible":false},"120":{"slot":120,"name":"Overwrite","elements":{"1":{"slot":1,"values":{"1":{"slot":1,"type":"STRING","value":"True"}}}},"visible":true},"121":{"slot":121,"name":"Single File","elements":{"1":{"slot":1,"values":{"1":{"slot":1,"type":"STRING","value":"True"}}}},"visible":true},"122":{"slot":122,"name":"Max File Size","elements":{"1":{"slot":1,"values":{"1":{"slot":1,"type":"STRING","value":""}}}},"visible":true},"123":{"slot":123,"name":"Include Headers","elements":{"1":{"slot":1,"values":{"1":{"slot":1,"type":"STRING","value":"True"}}}},"visible":true},"140":{"slot":140,"name":"Encryption","elements":{"1":{"slot":1,"values":{"1":{"slot":1,"type":"STRING","value":"None"}}}},"visible":true},"141":{"slot":141,"name":"Master Key","elements":{"1":{"slot":1,"values":{"1":{"slot":1,"type":"STRING","value":""}}}},"visible":false},"142":{"slot":142,"name":"KMS Key Id","elements":{"1":{"slot":1,"values":{"1":{"slot":1,"type":"STRING","value":""}}}},"visible":false},"200":{"slot":200,"name":"Stage","elements":{"1":{"slot":1,"values":{"1":{"slot":1,"type":"STRING","value":"[Custom]"}}}},"visible":true},"201":{"slot":201,"name":"File Prefix","elements":{"1":{"slot":1,"values":{"1":{"slot":1,"type":"STRING","value":"matillion-examples/spatial/agg_qb.csv.gz"}}}},"visible":true}},"activationStatus":"ENABLED","outputIterationConnectorIDs":[],"inputIterationConnectorIDs":[]}},"successConnectors":{"4880":{"id":4880,"sourceID":4815,"targetID":4873},"4641":{"id":4641,"sourceID":4514,"targetID":4635},"4689":{"id":4689,"sourceID":4550,"targetID":4688},"4821":{"id":4821,"sourceID":4694,"targetID":4815},"4551":{"id":4551,"sourceID":4514,"targetID":4550},"4695":{"id":4695,"sourceID":4635,"targetID":4694},"4760":{"id":4760,"sourceID":4688,"targetID":4759},"4874":{"id":4874,"sourceID":4759,"targetID":4873},"5052":{"id":5052,"sourceID":5036,"targetID":5051}},"failureConnectors":{},"unconditionalConnectors":{"4516":{"id":4516,"sourceID":4512,"targetID":4514},"5037":{"id":5037,"sourceID":4873,"targetID":5036}},"trueConnectors":{},"falseConnectors":{},"iterationConnectors":{},"noteConnectors":{},"canUndo":true,"undoCommand":"Set Parameter","undoCreated":1638283517303,"canRedo":false,"redoCommand":"","redoCreated":1638283156610,"notes":{"4510":{"id":4510,"x":-634,"y":-153,"width":577,"height":79,"text":"You **must** supply a default value for the following variables:\n\n**examples_storage** (E.g. if your S3 bucket is named s3://the-bucket then set the default value to **the-bucket**)\n**examples_schema** (name of a Snowflake schema)\n","colour":"f9c21b"},"4545":{"id":4545,"x":20,"y":-148,"width":127,"height":284,"text":"Copy files from GitHub into S3 cloud storage","colour":"00ce4f"},"4677":{"id":4677,"x":195,"y":-148,"width":127,"height":284,"text":"Recreate Snowflake staging tables","colour":"00ce4f"},"4681":{"id":4681,"x":372,"y":-148,"width":127,"height":284,"text":"Load the raw input data into the Snowflake staging tables","colour":"00ce4f"},"4886":{"id":4886,"x":656,"y":-85,"width":122,"height":168,"text":"Perform the spatial data integration","colour":"00ce4f"},"5164":{"id":5164,"x":811,"y":-85,"width":140,"height":168,"text":"Export the aggregated results for use downstream (reverse ETL)","colour":"00ce4f"}},"variables":{},"grids":{}},"info":{"id":4509,"name":"example PB2002 extract and load","description":"","type":"ORCHESTRATION","tag":"e6b3c475-36a3-4eb9-a3f7-bc3d13c01df3"},"path":["matillion-examples","spatial"]}],"version":"1.48.3","environment":"snowflake"}